README.rst
connection_url.py
setup.cfg
setup.py
django_connection_url.egg-info/PKG-INFO
django_connection_url.egg-info/SOURCES.txt
django_connection_url.egg-info/dependency_links.txt
django_connection_url.egg-info/not-zip-safe
django_connection_url.egg-info/top_level.txt